SSOPDataBase/__init__.py
SSOPDataBase/clientSubscriber.py
SSOPDataBase/database.sqlite
SSOPDataBase/gBaseDB.py
SSOPDataBase/gCentralComponentDB.py
SSOPDataBase/sBessMeasurementDataDB.py
SSOPDataBase/sBessSetPointDataDB.py
SSOPDataBase/sInvertorData.py
SSOPDataBase/sMeasureDB.py
SSOPDataBase/sPVGeneratorData.py
SSOPDataBase/sPVGeneratorSetPoint.py
SSOPDataBase/sServiceArbitrage.py
SSOPDataBase/sServicePeakShaving.py
SSOPDataBase/sServiceSelfConsumption.py
SSOPDataBase/sVariableList.py
SSOPDataBase/wGeneralDBService.py
SSOPDataBase/wMqttService.py
ssopdatabase-0.1.1.dist-info/METADATA
ssopdatabase-0.1.1.dist-info/WHEEL
ssopdatabase-0.1.1.dist-info/RECORD
